shareadb/__init__.py
shareadb/adb_client.py
shareadb/cli.py
shareadb/device_manager.py
shareadb/tcp_proxy.py
shareadb-0.1.1.dist-info/licenses/LICENSE
shareadb-0.1.1.dist-info/METADATA
shareadb-0.1.1.dist-info/WHEEL
shareadb-0.1.1.dist-info/entry_points.txt
shareadb-0.1.1.dist-info/top_level.txt
shareadb-0.1.1.dist-info/RECORD
