Metadata-Version: 2.4
Name: shareadb
Version: 0.1.1
Summary: Share local adb devices with remote users via TCP proxy
Author-email: hemin0721 <hemin0721@thundersoft.com>
Maintainer-email: hemin0721 <hemin0721@thundersoft.com>
License: MIT
Project-URL: Homepage, https://github.com/hemin0721/shareadb
Project-URL: Documentation, https://github.com/hemin0721/shareadb/blob/main/README.md
Project-URL: Repository, https://github.com/hemin0721/shareadb.git
Project-URL: Bug Tracker, https://github.com/hemin0721/shareadb/issues
Project-URL: Source Code, https://github.com/hemin0721/shareadb
Keywords: adb,android,tcp-proxy,device-sharing,remote-access
Classifier: Development Status :: 4 - Beta
Classifier: Intended Audience :: Developers
Classifier: Topic :: Software Development :: Testing
Classifier: Topic :: System :: Networking
Classifier: License :: OSI Approved :: MIT License
Classifier: Programming Language :: Python :: 3
Classifier: Programming Language :: Python :: 3.8
Classifier: Programming Language :: Python :: 3.9
Classifier: Programming Language :: Python :: 3.10
Classifier: Programming Language :: Python :: 3.11
Classifier: Programming Language :: Python :: 3.12
Classifier: Operating System :: OS Independent
Classifier: Operating System :: POSIX :: Linux
Classifier: Operating System :: Microsoft :: Windows
Classifier: Operating System :: MacOS
Requires-Python: >=3.8
License-File: LICENSE
Dynamic: license-file
